setup.cfg
setup.py
fileversioninger/__init__.py
fileversioninger/tool.py
fileversioninger.egg-info/PKG-INFO
fileversioninger.egg-info/SOURCES.txt
fileversioninger.egg-info/dependency_links.txt
fileversioninger.egg-info/top_level.txt
tests/__init__.py
tests/asserts.py
tests/versioning_test.py