Metadata-Version: 1.1
Name: fileversioninger
Version: 0.6
Summary: Easily append a meaningful file name to the end of a given file name.
Home-page: https://github.com/dwickstrom/fileversioninger
Author: David Wickstrom
Author-email: davidwickstrom@gmail.com
License: MIT
Platform: UNKNOWN
Classifier: Intended Audience :: Developers
Classifier: License :: OSI Approved :: BSD License
Classifier: Operating System :: OS Independent
Classifier: Programming Language :: Python :: 2.7
Classifier: Programming Language :: Python :: 3
Classifier: Topic :: Software Development
Classifier: Topic :: Software Development :: Libraries
Classifier: Topic :: Utilities
